cacgmm/__init__.py
cacgmm/cacg.py
cacgmm/cacg_trainer.py
cacgmm/cacgmm.py
cacgmm/cacgmm_trainer.py
cacgmm/utils.py
cacgmm_gpu-0.1.0.dist-info/LICENSE
cacgmm_gpu-0.1.0.dist-info/METADATA
cacgmm_gpu-0.1.0.dist-info/WHEEL
cacgmm_gpu-0.1.0.dist-info/top_level.txt
cacgmm_gpu-0.1.0.dist-info/RECORD
